atta/__init__.py
atta/agents/__init__.py
atta/ai/__init__.py
atta/ai/conversations/__init__.py
atta/ai/conversations/role.py
atta/ai/protocols/__init__.py
atta/ai/protocols/_types.py
atta/ai/protocols/llm.py
atta/ai/responses/__init__.py
atta/ai/responses/common/__init__.py
atta/ai/responses/common/content.py
atta/ai/responses/common/function_call.py
atta/ai/responses/common/message.py
atta/ai/responses/common/reasoning.py
atta/ai/responses/common/usage.py
atta/ai/responses/exception.py
atta/ai/responses/standard/__init__.py
atta/ai/responses/standard/text.py
atta/ai/responses/streaming/__init__.py
atta/ai/responses/streaming/_field.py
atta/ai/responses/streaming/text.py
atta/ai/responses/types.py
atta/config/__init__.py
atta/exceptions/__init__.py
atta/infra/__init__.py
atta/infra/cache/__init__.py
atta/infra/db/__init__.py
atta/infra/pubsub/__init__.py
atta/infra/pubsub/bus.py
atta/infra/pubsub/protocols.py
atta/infra/pubsub/topic.py
atta/infra/storage/__init__.py
atta/infra/vector/__init__.py
atta/memory/__init__.py
atta/observability/__init__.py
atta/observability/conventions/__init__.py
atta/observability/conventions/agents.py
atta/observability/conventions/genai.py
atta/observability/conventions/http.py
atta/observability/conventions/network.py
atta/observability/conventions/system.py
atta/observability/logging/__init__.py
atta/observability/logging/protocol.py
atta/observability/monitoring/__init__.py
atta/observability/tracing/__init__.py
atta/observability/tracing/attributes.py
atta/observability/tracing/common.py
atta/observability/tracing/noop.py
atta/observability/tracing/opentelemetry.py
atta/observability/tracing/typing.py
atta/py.typed
atta/utils/__init__.py
atta/utils/attributes.py
atta/utils/func.py
atta/utils/json.py
atta/utils/retry.py
atta/utils/signals.py
atta/utils/singleton.py
atta/utils/time.py
atta/utils/unique.py
atta-0.4.0.dist-info/WHEEL
atta-0.4.0.dist-info/METADATA
atta-0.4.0.dist-info/RECORD
