Metadata-Version: 2.3
Name: atta
Version: 0.4.0
Summary: Attachable AI building blocks for creating flexible, modular AI-driven applications.
Keywords: AI,framework,LLM,components
Author: Florian Peschke
Author-email: Florian Peschke <tech@florian-peschke.de>
Classifier: Development Status :: 3 - Alpha
Classifier: Intended Audience :: Developers
Classifier: License :: OSI Approved :: MIT License
Classifier: Programming Language :: Python :: 3.13
Classifier: Topic :: Scientific/Engineering :: Artificial Intelligence
Classifier: Typing :: Typed
Requires-Dist: attrs>=25.3.0
Requires-Dist: opentelemetry-sdk>=1.37.0
Requires-Dist: orjson>=3.11.3
Requires-Dist: pendulum>=3.1.0
Requires-Dist: atta-openai ; extra == 'ai'
Requires-Dist: atta-openai ; extra == 'all'
Requires-Dist: atta-openai ; extra == 'openai'
Requires-Python: >=3.13
Project-URL: Homepage, https://github.com/florianpeschke/atta
Project-URL: Issues, https://github.com/florianpeschke/atta/issues
Project-URL: Repository, https://github.com/florianpeschke/atta
Provides-Extra: ai
Provides-Extra: all
Provides-Extra: openai
